uMAIA/__init__.py
uMAIA/molecule_matching/__init__.py
uMAIA/molecule_matching/_match.py
uMAIA/molecule_matching/_moleculematch.py
uMAIA/normalization/__init__.py
uMAIA/normalization/_initialize.py
uMAIA/normalization/_model.py
uMAIA/normalization/_normalize.py
uMAIA/normalization/_transform.py
uMAIA/peak_finding/__init__.py
uMAIA/peak_finding/__main__.py
uMAIA/peak_finding/_run.py
uMAIA/peak_finding/peak_finder.py
uMAIA/utils/ImzMLParser.py
uMAIA/utils/__init__.py
uMAIA/utils/mspec.py
uMAIA/utils/tools.py
uMAIA/visualization/__init__.py
uMAIA/visualization/_visualization.py
uMAIA-0.2.dist-info/LICENSE.md
uMAIA-0.2.dist-info/METADATA
uMAIA-0.2.dist-info/WHEEL
uMAIA-0.2.dist-info/top_level.txt
uMAIA-0.2.dist-info/RECORD
