Metadata-Version: 2.1
Name: uMAIA
Version: 0.2
Summary: Toolbox for the processing and analysis of MALDI-MSI data
Home-page: https://github.com/lamanno-epfl/uMAIA
Author: @lamanno-epfl
Author-email: gioele.lamanno@epfl.ch
License-File: LICENSE.md
Requires-Dist: absl-py ==1.4.0
Requires-Dist: anndata ==0.9.2
Requires-Dist: asciitree ==0.3.3
Requires-Dist: chex ==0.1.82
Requires-Dist: cmake ==3.27.2
Requires-Dist: contourpy ==1.1.0
Requires-Dist: cycler ==0.11.0
Requires-Dist: fasteners ==0.18
Requires-Dist: filelock ==3.12.2
Requires-Dist: fonttools ==4.42.0
Requires-Dist: funsor ==0.4.5
Requires-Dist: gurobipy ==10.0.2
Requires-Dist: h5py ==3.9.0
Requires-Dist: jax ==0.4.14
Requires-Dist: jaxlib ==0.4.14
Requires-Dist: joblib ==1.3.2
Requires-Dist: kiwisolver ==1.4.4
Requires-Dist: lit ==16.0.6
Requires-Dist: llvmlite ==0.41.0
Requires-Dist: makefun ==1.15.1
Requires-Dist: matplotlib ==3.7.2
Requires-Dist: ml-dtypes ==0.2.0
Requires-Dist: more-itertools ==10.1.0
Requires-Dist: mpmath ==1.3.0
Requires-Dist: multipledispatch ==1.0.0
Requires-Dist: natsort ==8.4.0
Requires-Dist: networkx ==3.1
Requires-Dist: numba ==0.58.0
Requires-Dist: numcodecs ==0.11.0
Requires-Dist: numpy ==1.25.2
Requires-Dist: numpyro ==0.12.1
Requires-Dist: opencv-python ==4.8.0.76
Requires-Dist: opt-einsum ==3.3.0
Requires-Dist: optax ==0.1.7
Requires-Dist: pandas ==2.0.3
Requires-Dist: pillow ==10.0.0
Requires-Dist: pyimzml ==1.5.3
Requires-Dist: pymzml ==2.5.2
Requires-Dist: pyparsing ==3.0.9
Requires-Dist: pyro-api ==0.1.2
Requires-Dist: pyro-ppl ==1.8.6
Requires-Dist: regex ==2023.8.8
Requires-Dist: scikit-learn ==1.3.0
Requires-Dist: scipy ==1.11.1
Requires-Dist: seaborn ==0.12.2
Requires-Dist: sympy ==1.12
Requires-Dist: threadpoolctl ==3.2.0
Requires-Dist: toolz ==0.12.0
Requires-Dist: torch ==2.0.1
Requires-Dist: tqdm ==4.66.1
Requires-Dist: tzdata ==2023.3
Requires-Dist: wheezy-template ==3.2.1
Requires-Dist: xmltodict ==0.13.0
Requires-Dist: zarr ==2.16.0
Requires-Dist: lxml ==4.9.3
Requires-Dist: notebook
